simplecrypto/__init__.py
simplecrypto/exceptions.py
simplecrypto/formats.py
simplecrypto/guess.py
simplecrypto/hashes.py
simplecrypto/key.py
simplecrypto/random.py
simplecrypto/tests/__init__.py
simplecrypto-0.3.4.dist-info/LICENSE.txt
simplecrypto-0.3.4.dist-info/METADATA
simplecrypto-0.3.4.dist-info/WHEEL
simplecrypto-0.3.4.dist-info/top_level.txt
simplecrypto-0.3.4.dist-info/RECORD
