Metadata-Version: 2.1
Name: simplecrypto
Version: 0.3.4
Summary: Simple cryptographic library for hashing and encrypting
Home-page: https://github.com/boppreh/simplecrypto
Author: BoppreH
Author-email: github@boppreh.com
License: MIT
Keywords: simple cryptography symmetric asymmetric hash encrypt decrypt rsa aes sha md5
Classifier: Development Status :: 3 - Alpha
Classifier: Topic :: Security :: Cryptography
Classifier: License :: OSI Approved :: MIT License
Classifier: Intended Audience :: Developers
Classifier: Natural Language :: English
Classifier: Operating System :: OS Independent
Classifier: Programming Language :: Python :: 3.3
Classifier: Topic :: Software Development :: Libraries :: Python Modules
License-File: LICENSE.txt
Requires-Dist: PyCrypto
